{
  "collectionName": "components_home_page_service_sections",
  "info": {
    "displayName": "Service Section"
  },
  "options": {},
  "attributes": {
    "sectionTag": {
      "type": "string"
    },
    "title": {
      "type": "string"
    },
    "description": {
      "type": "text"
    },
    "ctaButton": {
      "type": "component",
      "component": "shared.cta-button",
      "repeatable": false
    },
    "services": {
      "type": "component",
      "component": "home-page-components.service-card",
      "repeatable": true
    },
    "featuredServices": {
      "type": "component",
      "component": "home-page-components.service-card",
      "repeatable": true
    }
  },
  "config": {}
}
